math_operations/__init__.py
math_operations/operations.py
math_utilsn-0.1.1.dist-info/LICENSE
math_utilsn-0.1.1.dist-info/METADATA
math_utilsn-0.1.1.dist-info/WHEEL
math_utilsn-0.1.1.dist-info/entry_points.txt
math_utilsn-0.1.1.dist-info/top_level.txt
math_utilsn-0.1.1.dist-info/RECORD
